blockpipe/__init__.py
blockpipe-0.1.3.dist-info/LICENSE
blockpipe-0.1.3.dist-info/METADATA
blockpipe-0.1.3.dist-info/WHEEL
blockpipe-0.1.3.dist-info/RECORD
