Metadata-Version: 2.1
Name: blockpipe
Version: 0.1.3
Summary: 
Author: Sorawit Suriyakarn
Author-email: thepsint@gmail.com
Requires-Python: >=3.6
Classifier: Programming Language :: Python :: 3
Classifier: Programming Language :: Python :: 3.6
Classifier: Programming Language :: Python :: 3.7
Classifier: Programming Language :: Python :: 3.8
Classifier: Programming Language :: Python :: 3.9
Classifier: Programming Language :: Python :: 3.10
Classifier: Programming Language :: Python :: 3.11
Requires-Dist: requests (>=2.30.0,<3.0.0)
